{
  "summary": {
    "name": "Nieuwsgierigen",
    "description": "Jullie nieuwsgierigheid groeit en jullie zijn klaar om uit je comfortzone te stappen. Ontdek spannende uitdagingen die jullie nog dichter bij elkaar brengen, terwijl het speels en spontaan blijft!",
    "couple_type": "hetero",
    "play_presence": true,
    "language": "nl",
    "total_quests": 51,
    "required_tools": [],
    "tags": ["vaginal_sex", "oral_sex"]
  },
  "quests": [

    {
      "moment": "early",
      "required_tools": [],
      "player_type": "both",
      "timer": 2,
      "content": "Streel en kus elkaar staand gedurende 2 minuten."
    },
    {
      "moment": "early",
      "required_tools": [],
      "player_type": "both",
      "timer": 2,
      "content": "Sluit je ogen terwijl je partner iets opwindends in je oor fluistert en je lichaam streelt gedurende 2 minuten."
    },
    {
      "moment": "early",
      "required_tools": [],
      "player_type": "both",
      "timer": 0,
      "content": "Schrijf op een briefje iets dat je opwindt en wissel het uit aan het einde van de volgende beurt."
    },
    {
      "moment": "early",
      "required_tools": [],
      "player_type": "both",
      "timer": 1,
      "content": "Je partner kust je hele lichaam gedurende 1 minuut."
    },
    {
      "moment": "early",
      "required_tools": [],
      "player_type": "both",
      "timer": 0,
      "content": "Je partner schrijft een spannend woord op je lichaam met zijn/haar vingertoppen en jij moet het raden."
    },
    {
      "moment": "early",
      "required_tools": [],
      "player_type": "both",
      "timer": 2,
      "content": "Streel elkaar met gesloten ogen gedurende 2 minuten."
    },
    {
      "moment": "early",
      "required_tools": [],
      "player_type": "both",
      "timer": 1,
      "content": "Ga achter je partner zitten en streel hem/haar terwijl je zijn/haar nek kust gedurende 1 minuut."
    },
    {
      "moment": "early",
      "required_tools": [],
      "player_type": "both",
      "timer": 0,
      "content": "Breng een van je fantasieën over naar je partner door alleen lichaamstaal te gebruiken."
    },
    {
      "moment": "early",
      "required_tools": [],
      "player_type": "both",
      "timer": 2,
      "content": "Breng jullie gezichten dicht bij elkaar en kijk elkaar in de ogen zonder te kussen gedurende 2 minuten."
    },
    {
      "moment": "early",
      "required_tools": [],
      "player_type": "both",
      "timer": 2,
      "content": "Ga op de rug van je partner zitten en geef hem/haar een massage gedurende 2 minuten."
    },
    {
      "moment": "early",
      "required_tools": [],
      "player_type": "both",
      "timer": 0,
      "content": "Zoek samen online een nieuwe positie om uit te proberen."
    },
    {
      "moment": "early",
      "required_tools": [],
      "player_type": "both",
      "timer": 0,
      "content": "Kleed de andere speler voorzichtig uit tot hij/zij alleen nog ondergoed draagt."
    },
    {
      "moment": "mid",
      "required_tools": [],
      "player_type": "both",
      "timer": 1,
      "content": "Koel je handen af met koud water en streel het lichaam van je partner gedurende 1 minuut."
    },
    {
      "moment": "mid",
      "required_tools": [],
      "player_type": "both",
      "timer": 0,
      "content": "Fluister om de beurt drie fantasieën die jullie zouden willen realiseren."
    },
    {
      "moment": "mid",
      "required_tools": [],
      "player_type": "both",
      "timer": 0,
      "content": "Je partner kiest jouw outfit voor de rest van het spel."
    },
    {
      "moment": "mid",
      "required_tools": [],
      "player_type": "both",
      "timer": 3,
      "content": "Ga achter de andere speler zitten en masturbeer hem/haar gedurende 3 minuten terwijl je zijn/haar nek kust en opwindende dingen fluistert."
    },
    {
      "moment": "mid",
      "required_tools": [],
      "player_type": "both",
      "timer": 2,
      "content": "Probeer het hartritme van je partner te volgen terwijl je hem/haar masturbeert gedurende 2 minuten."
    },
    {
      "moment": "mid",
      "required_tools": [],
      "player_type": "both",
      "timer": 3,
      "content": "Doe aan sexting via jullie favoriete berichtapp gedurende 3 minuten."
    },
    {
      "moment": "mid",
      "required_tools": [],
      "player_type": "both",
      "timer": 2,
      "content": "Ga naast elkaar zitten en masturbeer elkaar gedurende 2 minuten."
    },
    {
      "moment": "mid",
      "required_tools": [],
      "player_type": "both",
      "timer": 1,
      "content": "Doe een sexy dansje van 1 minuut voor de andere speler."
    },
    {
      "moment": "mid",
      "required_tools": [],
      "player_type": "both",
      "timer": 0,
      "content": "Onderdruk geen enkel geluid of woord tijdens seksuele handelingen tot het einde van het spel."
    },
    {
      "moment": "late",
      "required_tools": [],
      "player_type": "both",
      "timer": 3,
      "content": "Masturbeer elkaar gedurende 3 minuten terwijl jullie gezichten dicht bij elkaar zijn maar zonder te kussen."
    },
    {
      "moment": "late",
      "required_tools": [],
      "player_type": "both",
      "timer": 0,
      "content": "Je partner masturbeert je totdat je bijna klaarkomt en stopt dan (edging)."
    },
    {
      "moment": "late",
      "required_tools": [],
      "player_type": "both",
      "timer": 2,
      "content": "Schakel alle lichtbronnen uit en streel elkaar naakt gedurende 2 minuten."
    },
    {
      "moment": "late",
      "required_tools": [],
      "player_type": "both",
      "timer": 3,
      "content": "Masturbeer de andere speler terwijl je jezelf ook masturbeert gedurende 3 minuten."
    },
    {
      "moment": "end",
      "required_tools": [],
      "player_type": "both",
      "timer": 0,
      "content": "Eindig het spel op de manier die jullie het leukst vinden."
    },
    {
      "moment": "end",
      "required_tools": [],
      "player_type": "both",
      "timer": 0,
      "content": "Sluit het spel af met een penetratieve vrijpartij in een positie naar keuze."
    },
    {
      "moment": "end",
      "required_tools": [],
      "player_type": "both",
      "timer": 0,
      "content": "Masturbeer de andere speler tot hij/zij klaarkomt."
    },
    {
      "moment": "mid",
      "required_tools": [],
      "player_type": "both",
      "timer": 0,
      "content": "Speel een rollenspel waarbij jullie een opwindende setting kiezen."
    },
    {
      "moment": "mid",
      "required_tools": [],
      "player_type": "both",
      "timer": 1,
      "content": "Je partner brengt zijn/haar gezicht dicht bij je intieme delen gedurende 1 minuut zonder je aan te raken."
    },
    {
      "moment": "mid",
      "required_tools": [],
      "player_type": "both",
      "timer": 2,
      "content": "Je partner leidt je hand om zichzelf te masturberen gedurende 2 minuten."
    },
    {
      "moment": "mid",
      "required_tools": [],
      "player_type": "both",
      "timer": 1,
      "content": "Je partner streelt en ademt zachtjes op je erogene zones gedurende 1 minuut zonder meer te doen."
    },
    {
      "moment": "mid",
      "required_tools": [],
      "player_type": "both",
      "timer": 0,
      "content": "Je partner doet een sexy striptease voor jou."
    },
    {
      "moment": "mid",
      "required_tools": [],
      "player_type": "both",
      "timer": 0,
      "content": "Trek het ondergoed van de andere speler uit zonder je handen te gebruiken."
    },
    {
      "moment": "mid",
      "required_tools": [],
      "player_type": "both",
      "timer": 1,
      "content": "Lik zachtjes de intieme delen van de andere speler gedurende 1 minuut."
    },
    {
      "moment": "mid",
      "required_tools": [],
      "player_type": "both",
      "timer": 2,
      "content": "Ga onder een tafel zitten en geef de andere speler orale seks gedurende 2 minuten."
    },
    {
      "moment": "mid",
      "required_tools": [],
      "player_type": "both",
      "timer": 3,
      "content": "Sta achter de andere speler voor een spiegel en masturbeer hem/haar gedurende 3 minuten."
    },
    {
      "moment": "late",
      "required_tools": [],
      "player_type": "both",
      "timer": 3,
      "content": "Kniel voor je partner neer en geef hem/haar orale seks gedurende 3 minuten."
    },
    {
      "moment": "late",
      "required_tools": [],
      "player_type": "both",
      "timer": 0,
      "content": "Je partner geeft je orale seks totdat je bijna klaarkomt en stopt dan (edging)."
    },
    {
      "moment": "late",
      "required_tools": [],
      "player_type": "both",
      "timer": 1,
      "content": "Kus de intieme delen van je partner gedurende 1 minuut."
    },
    {
      "moment": "late",
      "required_tools": [],
      "player_type": "both",
      "timer": 3,
      "content": "Doe een negenenzestig met je partner gedurende 3 minuten."
    },
    {
      "moment": "late",
      "required_tools": [],
      "player_type": "both",
      "timer": 2,
      "content": "Geef orale seks aan de andere speler terwijl je jezelf masturbeert gedurende 2 minuten."
    },
    {
      "moment": "late",
      "required_tools": [],
      "player_type": "both",
      "timer": 3,
      "content": "Geef orale seks aan de andere speler terwijl je jezelf masturbeert gedurende 3 minuten in doggy style."
    },
    {
      "moment": "late",
      "required_tools": [],
      "player_type": "both",
      "timer": 2,
      "content": "De andere speler zit in doggy style terwijl jij hem/haar orale seks geeft gedurende 2 minuten."
    },
    {
      "moment": "end",
      "required_tools": [],
      "player_type": "both",
      "timer": 5,
      "content": "Doe een negenenzestig met je partner gedurende 5 minuten."
    },
    {
      "moment": "end",
      "required_tools": [],
      "player_type": "both",
      "timer": 0,
      "content": "Kniel voor je partner neer en geef hem/haar orale seks totdat hij/zij klaarkomt."
    },
    {
      "moment": "end",
      "required_tools": [],
      "player_type": "male",
      "timer": 0,
      "content": "Je vrouwelijke partner gaat op je gezicht zitten en je geeft haar orale seks totdat ze klaarkomt."
    },
    {
      "moment": "end",
      "required_tools": [],
      "player_type": "both",
      "timer": 0,
      "content": "Sluit het spel af met een penetratieve vrijpartij in missionarishouding."
    },
    {
      "moment": "end",
      "required_tools": [],
      "player_type": "both",
      "timer": 0,
      "content": "Sluit het spel af met een penetratieve vrijpartij in cowgirlhouding."
    },
    {
      "moment": "end",
      "required_tools": [],
      "player_type": "both",
      "timer": 0,
      "content": "Sluit het spel af met een penetratieve vrijpartij in doggy style."
    },
    {
      "moment": "end",
      "required_tools": [],
      "player_type": "both",
      "timer": 0,
      "content": "Sluit het spel af met een penetratieve vrijpartij in reverse cowgirlhouding."
    }
  ]
}
