{
  "summary": {
    "name": "Désir Numérique",
    "description": "Un deck pour ceux qui veulent dépasser les barrières de l’écran et se laisser emporter par le jeu de l’excitation. Messages audacieux, contenus torrides et fantasmes explicites se mêlent pour une connexion brûlante à distance.",
    "couple_type": "hetero",
    "play_presence": false,
    "language": "fr",
    "total_quests": 20,
    "required_tools": [],
    "tags": ["chat"]
  },
  "quests": [
    {
      "moment": "early",
      "required_tools": [],
      "player_type": "both",
      "timer": 0,
      "content": "Décris en détail comment tu te caresserais en ce moment si ton/ta partenaire te regardait."
    },
    {
      "moment": "early",
      "required_tools": [],
      "player_type": "both",
      "timer": 0,
      "content": "Envoie une photo sexy en sous-vêtements ou partiellement nu(e), avec un message : 'Et ce n’est que le début...'"
    },
    {
      "moment": "early",
      "required_tools": [],
      "player_type": "both",
      "timer": 0,
      "content": "Enregistre un audio où tu décris à quoi ressemblerait ton souffle juste avant l’orgasme."
    },
    {
      "moment": "early",
      "required_tools": [],
      "player_type": "both",
      "timer": 0,
      "content": "Raconte un fantasme sexuel réel que tu as eu sur ton/ta partenaire, même s’il/elle ne le sait pas."
    },
    {
      "moment": "early",
      "required_tools": [],
      "player_type": "both",
      "timer": 0,
      "content": "Écris un message décrivant avec précision ce que tu voudrais que ton/ta partenaire fasse avec sa bouche."
    },
    {
      "moment": "mid",
      "required_tools": [],
      "player_type": "both",
      "timer": 0,
      "content": "Envoie une photo nue ou presque, avec une seule partie de ton corps entièrement visible. Laisse deviner le reste."
    },
    {
      "moment": "mid",
      "required_tools": [],
      "player_type": "both",
      "timer": 0,
      "content": "Écris un texte érotique de 4 lignes décrivant un rapport sexuel imaginaire entre vous deux. Utilise des mots explicites."
    },
    {
      "moment": "mid",
      "required_tools": [],
      "player_type": "both",
      "timer": 0,
      "content": "Enregistre un vocal où tu gémis doucement quelques secondes comme si ton/ta partenaire te touchait."
    },
    {
      "moment": "mid",
      "required_tools": [],
      "player_type": "both",
      "timer": 0,
      "content": "Décris par message une scène où tu domines ton/ta partenaire. Excite-le/la avec des mots puissants."
    },
    {
      "moment": "mid",
      "required_tools": [],
      "player_type": "both",
      "timer": 0,
      "content": "Écris comment tu te masturberais en pensant à ton/ta partenaire en ce moment. En détail, sans censure."
    },
    {
      "moment": "late",
      "required_tools": [],
      "player_type": "both",
      "timer": 0,
      "content": "Écris un message où tu le/la guides verbalement jusqu’à l’orgasme : étape par étape, ordre après ordre."
    },
    {
      "moment": "late",
      "required_tools": [],
      "player_type": "both",
      "timer": 0,
      "content": "Envoie une vidéo où tu caresses lentement ton sexe par-dessus tes vêtements, sans parler, juste avec le regard."
    },
    {
      "moment": "late",
      "required_tools": [],
      "player_type": "both",
      "timer": 0,
      "content": "Écris un message avec une description explicite de ta dernière expérience sexuelle avec ton/ta partenaire."
    },
    {
      "moment": "late",
      "required_tools": [],
      "player_type": "both",
      "timer": 0,
      "content": "Envoie une photo en gros plan de l’une de tes zones érogènes préférées, sans filtre."
    },
    {
      "moment": "late",
      "required_tools": [],
      "player_type": "both",
      "timer": 0,
      "content": "Écris une histoire hot à la première personne : tu entres dans sa chambre et tu le/la prends sans dire un mot."
    },
    {
      "moment": "end",
      "required_tools": [],
      "player_type": "both",
      "timer": 0,
      "content": "Fais une liste dans le chat des 3 choses les plus osées que tu voudrais essayer avec ton/ta partenaire en vrai."
    },
    {
      "moment": "end",
      "required_tools": [],
      "player_type": "both",
      "timer": 0,
      "content": "Écris à ton/ta partenaire ce que tu veux qu’il/elle te fasse, en détail, jusqu’à l’orgasme."
    },
    {
      "moment": "end",
      "required_tools": [],
      "player_type": "both",
      "timer": 0,
      "content": "Envoie un vocal dans lequel tu t’imagines jouir, en décrivant l’émotion et la sensation le plus réalistement possible."
    },
    {
      "moment": "end",
      "required_tools": [],
      "player_type": "both",
      "timer": 0,
      "content": "Termine le jeu en envoyant un selfie post-orgasme (réel ou simulé), accompagné de seulement deux mots."
    },
    {
      "moment": "end",
      "required_tools": [],
      "player_type": "both",
      "timer": 0,
      "content": "Écris à ton/ta partenaire : 'La prochaine fois qu’on se voit, je te ferai...' et complète avec ton désir le plus audacieux."
    }
  ]
}
