{
  "summary": {
    "name": "爱之缠绵",
    "description": "准备迎接极致欢愉！这套卡牌将带您经历想象力与欲望的狂野旅程，只适合那些渴望彻底放纵的玩家",
    "couple_type": "hetero",
    "play_presence": true,
    "language": "zh",
    "total_quests": 38,
    "required_tools": [],
    "tags": ["vaginal_sex", "oral_sex"],
    "difficulty": "advanced"
  },
  "quests": [
    {
      "moment": "early",
      "required_tools": [],
      "player_type": "both",
      "timer": 2,
      "content": "站立相拥爱抚接吻2分钟"
    },
    {
      "moment": "early",
      "required_tools": [],
      "player_type": "both",
      "timer": 1,
      "content": "伴侣让你仅着内衣，用1分钟吻遍全身"
    },
    {
      "moment": "early",
      "required_tools": [],
      "player_type": "both",
      "timer": 1,
      "content": "从背后环抱伴侣，边吻颈边爱抚1分钟"
    },
    {
      "moment": "early",
      "required_tools": [],
      "player_type": "both",
      "timer": 1,
      "content": "脸贴脸对视1分钟但不接吻"
    },
    {
      "moment": "early",
      "required_tools": [],
      "player_type": "both",
      "timer": 0,
      "content": "温柔地为对方褪去衣物直到只剩内衣"
    },
    {
      "moment": "early",
      "required_tools": [],
      "player_type": "both",
      "timer": 0,
      "content": "让伴侣为你选择游戏剩余时间的着装"
    },
    {
      "moment": "mid",
      "required_tools": [],
      "player_type": "both",
      "timer": 0,
      "content": "承诺在后续性爱中完全释放声音和语言"
    },
    {
      "moment": "mid",
      "required_tools": [],
      "player_type": "both",
      "timer": 2,
      "content": "从背后爱抚伴侣私处2分钟，同时吻颈说情话"
    },
    {
      "moment": "mid",
      "required_tools": [],
      "player_type": "both",
      "timer": 2,
      "content": "尝试同步伴侣心跳节奏爱抚其私处2分钟"
    },
    {
      "moment": "mid",
      "required_tools": [],
      "player_type": "both",
      "timer": 3,
      "content": "用最爱社交软件互发色情消息3分钟"
    },
    {
      "moment": "mid",
      "required_tools": [],
      "player_type": "both",
      "timer": 0,
      "content": "让伴侣爱抚你直到临近高潮再停止(边缘控制)"
    },
    {
      "moment": "mid",
      "required_tools": [],
      "player_type": "both",
      "timer": 2,
      "content": "关灯热吻同时爱抚对方裸体2分钟"
    },
    {
      "moment": "mid",
      "required_tools": [],
      "player_type": "both",
      "timer": 0,
      "content": "选择性感角色扮演并持续到游戏结束"
    },
    {
      "moment": "mid",
      "required_tools": [],
      "player_type": "both",
      "timer": 2,
      "content": "让伴侣引导你用手爱抚其私处2分钟"
    },
    {
      "moment": "mid",
      "required_tools": [],
      "player_type": "both",
      "timer": 0,
      "content": "不用手帮伴侣脱下内裤"
    },
    {
      "moment": "mid",
      "required_tools": [],
      "player_type": "both",
      "timer": 1,
      "content": "1分钟温柔舔遍伴侣私处"
    },
    {
      "moment": "mid",
      "required_tools": [],
      "player_type": "both",
      "timer": 2,
      "content": "在桌下为伴侣口交2分钟"
    },
    {
      "moment": "mid",
      "required_tools": [],
      "player_type": "both",
      "timer": 3,
      "content": "站在镜前从背后爱抚伴侣私处3分钟"
    },
    {
      "moment": "mid",
      "required_tools": [],
      "player_type": "both",
      "timer": 0,
      "content": "一起观看情色短片讨论最兴奋的点"
    },
    {
      "moment": "mid",
      "required_tools": [],
      "player_type": "both",
      "timer": 0,
      "content": "让伴侣为你拍摄指定性感照片"
    },
    {
      "moment": "mid",
      "required_tools": [],
      "player_type": "both",
      "timer": 0,
      "content": "拍张性感照发给伴侣"
    },
    {
      "moment": "mid",
      "required_tools": [],
      "player_type": "both",
      "timer": 0,
      "content": "让伴侣用力拍打你的臀部"
    },
    {
      "moment": "late",
      "required_tools": [],
      "player_type": "both",
      "timer": 2,
      "content": "让伴侣控制你头部为其口交2分钟"
    },
    {
      "moment": "late",
      "required_tools": [],
      "player_type": "both",
      "timer": 2,
      "content": "将私处贴近伴侣脸部自慰2分钟"
    },
    {
      "moment": "late",
      "required_tools": [],
      "player_type": "both",
      "timer": 2,
      "content": "为伴侣口交同时自慰2分钟"
    },
    {
      "moment": "late",
      "required_tools": [],
      "player_type": "both",
      "timer": 0,
      "content": "让伴侣将私处放入你口中自慰1分钟——你不要动"
    },
    {
      "moment": "late",
      "required_tools": [],
      "player_type": "both",
      "timer": 2,
      "content": "跪姿为伴侣口交2分钟"
    },
    {
      "moment": "late",
      "required_tools": [],
      "player_type": "both",
      "timer": 0,
      "content": "让伴侣为你口交直到临近高潮再停止"
    },
    {
      "moment": "late",
      "required_tools": [],
      "player_type": "both",
      "timer": 2,
      "content": "与伴侣69式互舔2分钟"
    },
    {
      "moment": "late",
      "required_tools": [],
      "player_type": "male",
      "timer": 2,
      "content": "让伴侣摆出后入姿势并为其口交2分钟"
    },
    {
      "moment": "late",
      "required_tools": [],
      "player_type": "both",
      "timer": 0,
      "content": "让伴侣为你录制指定性感视频"
    },
    {
      "moment": "late",
      "required_tools": [],
      "player_type": "both",
      "timer": 0,
      "content": "录制性感视频发给伴侣"
    },
    {
      "moment": "end",
      "required_tools": [],
      "player_type": "both",
      "timer": 0,
      "content": "与伴侣69式互舔直至共同高潮"
    },
    {
      "moment": "end",
      "required_tools": [],
      "player_type": "both",
      "timer": 0,
      "content": "跪姿为伴侣口交直至其高潮"
    },
    {
      "moment": "end",
      "required_tools": [],
      "player_type": "male",
      "timer": 0,
      "content": "让女伴坐在脸上为其口交直至高潮"
    },
    {
      "moment": "end",
      "required_tools": [],
      "player_type": "both",
      "timer": 0,
      "content": "以女上位体位进行插入式性爱结束游戏"
    },
    {
      "moment": "end",
      "required_tools": [],
      "player_type": "both",
      "timer": 0,
      "content": "以后入式体位进行插入式性爱结束游戏"
    },
    {
      "moment": "end",
      "required_tools": [],
      "player_type": "both",
      "timer": 0,
      "content": "以反向女上位体位进行插入式性爱结束游戏"
    }
  ]
}
